virt_linked_clone/__init__.py
virt_linked_clone/__main__.py
virt_linked_clone/cli.py
virt_linked_clone/version.py
virt_linked_clone/virt_linked_clone.py
virt_linked_clone/zsh_completion.sh
virt_linked_clone-1.1.2.dist-info/LICENSE
virt_linked_clone-1.1.2.dist-info/METADATA
virt_linked_clone-1.1.2.dist-info/WHEEL
virt_linked_clone-1.1.2.dist-info/entry_points.txt
virt_linked_clone-1.1.2.dist-info/top_level.txt
virt_linked_clone-1.1.2.dist-info/RECORD
