Metadata-Version: 2.1
Name: virt-linked-clone
Version: 1.1.2
Summary: Create a shallow clone of a qcow2-backed LibVirt virtual machine
Author-email: "John T. Goetz" <theodore.goetz@gmail.com>
Project-URL: homepage, https://gitlab.com/johngoetz/virt-linked-clone
Keywords: virtualization,libvirt,clone,qemu,kvm,qcow2
Classifier: Development Status :: 4 - Beta
Classifier: Environment :: Console
Classifier: Intended Audience :: Developers
Classifier: Intended Audience :: Information Technology
Classifier: Intended Audience :: System Administrators
Classifier: License :: OSI Approved :: MIT License
Classifier: Natural Language :: English
Classifier: Operating System :: POSIX :: Linux
Classifier: Operating System :: Unix
Classifier: Programming Language :: Python :: 3 :: Only
Classifier: Programming Language :: Python :: 3
Classifier: Programming Language :: Python
Classifier: Topic :: Utilities
Requires-Python: >=3.8
License-File: LICENSE
Requires-Dist: libvirt-python
